README.md
setup.py
setupnovernormalize.py
setupnovernormalize.egg-info/PKG-INFO
setupnovernormalize.egg-info/SOURCES.txt
setupnovernormalize.egg-info/dependency_links.txt
setupnovernormalize.egg-info/top_level.txt