Metadata-Version: 2.1
Name: setupnovernormalize
Version: 1.0.1
Summary: Prevent version normalization when packaging Python projects with setuptools.
Home-page: https://github.com/ccrisan/setup-no-ver-normalize
Author: Calin Crisan
Author-email: ccrisan@gmail.com
License: UNLICENSE
Platform: UNKNOWN
